drawranflow/__init__.py
drawranflow/admin.py
drawranflow/apps.py
drawranflow/models.py
drawranflow/tests.py
drawranflow/urls.py
drawranflow/views.py
drawranflow/migrations/0001_initial.py
drawranflow/migrations/0002_uploadedfile_is_analysis_complete.py
drawranflow/migrations/__init__.py
drawranflow/servicelogic/processPackets.py
drawranflow/servicelogic/handlers/f1ap_handler.py
drawranflow/servicelogic/intfconfig/cos_codes.json
drawranflow/servicelogic/intfconfig/e1ap_proc.json
drawranflow/servicelogic/intfconfig/f1ap_proc.json
drawranflow/servicelogic/intfconfig/msg_directions.json
drawranflow/servicelogic/intfconfig/nas_proc.json
drawranflow/servicelogic/intfconfig/ngap_proc.json
drawranflow/servicelogic/intfconfig/rrc_proc.json
drawranflow/servicelogic/intfconfig/xnap_proc.json
drawranflow/templates/base copy.html
drawranflow/templates/base.html
drawranflow/templates/dbqueries
drawranflow/templates/draw_sequence copy.html
drawranflow/templates/draw_sequence.html
drawranflow/templates/home.html
drawranflow/templates/show_stats.html
drawranflow/templates/show_stats_bkup.html
drawranflow/templates/streaming_table.html
ranshark_drawranflow-1.0.8.dist-info/METADATA
ranshark_drawranflow-1.0.8.dist-info/WHEEL
ranshark_drawranflow-1.0.8.dist-info/top_level.txt
ranshark_drawranflow-1.0.8.dist-info/RECORD
